mkdocs_snippets/__init__.py
mkdocs_snippets/plugin.py
mkdocs_snippets-1.3.2.dist-info/licenses/LICENSE.txt
mkdocs_snippets-1.3.2.dist-info/METADATA
mkdocs_snippets-1.3.2.dist-info/WHEEL
mkdocs_snippets-1.3.2.dist-info/entry_points.txt
mkdocs_snippets-1.3.2.dist-info/top_level.txt
mkdocs_snippets-1.3.2.dist-info/RECORD
