Metadata-Version: 2.4
Name: mkdocs-snippets
Version: 1.3.2
Summary: Snippets for MkDocs
Author-email: CyberOtter <contact@betonquest.org>
License-Expression: MIT
Project-URL: Homepage, https://github.com/BetonQuest/mkdocs-snippets
Project-URL: Bug Tracker, https://github.com/BetonQuest/mkdocs-snippets/issues
Classifier: Development Status :: 5 - Production/Stable
Classifier: Intended Audience :: Developers
Classifier: Intended Audience :: Information Technology
Classifier: Programming Language :: Python
Classifier: Programming Language :: Python :: 3 :: Only
Requires-Python: >=3.8
License-File: LICENSE.txt
Dynamic: license-file
